data_crypto/__init__.py
data_crypto/decryptor.py
data_crypto/encryptor.py
data_crypto_szjh-0.1.3.dist-info/LICENSE
data_crypto_szjh-0.1.3.dist-info/METADATA
data_crypto_szjh-0.1.3.dist-info/WHEEL
data_crypto_szjh-0.1.3.dist-info/top_level.txt
data_crypto_szjh-0.1.3.dist-info/RECORD
