Metadata-Version: 2.1
Name: data-crypto-szjh
Version: 0.1.3
Summary: A tool for data encryption and decryption
Author-email: 周 <your.email@example.com>
Project-URL: Homepage, https://github.com/Hoodie-melon/JIAMI
Requires-Python: >=3.8
License-File: LICENSE
Requires-Dist: pymysql>=1.0.2
Requires-Dist: cryptography>=35.0.0
Requires-Dist: python-dotenv>=0.19.0
Requires-Dist: pandas>=1.3.0
Requires-Dist: DBUtils>=3.0.0
Requires-Dist: xlsxwriter>=3.0.0
